sview/__init__.py
sview/builder.py
sview/cli.py
sview/exceptions.py
sview/server.py
sphinx_view-0.3.1.dist-info/entry_points.txt
sphinx_view-0.3.1.dist-info/LICENSE.rst
sphinx_view-0.3.1.dist-info/WHEEL
sphinx_view-0.3.1.dist-info/METADATA
sphinx_view-0.3.1.dist-info/RECORD
