Metadata-Version: 2.1
Name: sphinx-view
Version: 0.3.1
Summary: View your rendered Sphinx or ReStructuredText documents in a browser
Home-page: https://sphinx-view.readthedocs.io/en/latest/
License: MIT
Author: Tucker Beck
Author-email: tucker.beck@gmail.com
Requires-Python: >=3.7,<4.0
Classifier: License :: OSI Approved :: MIT License
Classifier: Programming Language :: Python :: 3
Classifier: Programming Language :: Python :: 3.7
Classifier: Programming Language :: Python :: 3.8
Classifier: Programming Language :: Python :: 3.9
Requires-Dist: Flask (>=2.0.1,<3.0.0)
Requires-Dist: Sphinx (>=4.2.0,<5.0.0)
Requires-Dist: inflection (>=0.5.1,<0.6.0)
Requires-Dist: livereload (>=2.6.3,<3.0.0)
Requires-Dist: py-buzz (>=2.1.3,<3.0.0)
Requires-Dist: typer (>=0.4.0,<0.5.0)
Project-URL: Documentation, https://sphinx-view.readthedocs.io/en/latest/
Project-URL: Repository, https://github.com/dusktreader/spinx-view
